electricityapi/ElectricityMap.py
electricityapi/__init__.py
electricityapi-0.2.dev1.dist-info/LICENSE
electricityapi-0.2.dev1.dist-info/METADATA
electricityapi-0.2.dev1.dist-info/WHEEL
electricityapi-0.2.dev1.dist-info/top_level.txt
electricityapi-0.2.dev1.dist-info/RECORD
