Metadata-Version: 2.1
Name: electricityapi
Version: 0.2.dev1
Summary: This packages gives you interfaces to various providers of electricity grid data
Home-page: https://github.com/green-coding-berlin/electricityapi
Author: Didi Hoffmann
Author-email: didi@green-coding.berlin
License: GNU AFFERO GENERAL PUBLIC LICENSE
Classifier: Development Status :: 3 - Alpha
Classifier: Intended Audience :: Developers
Classifier: Programming Language :: Python :: 3
License-File: LICENSE
Requires-Dist: requests
